telegrampx/__init__.py
telegrampx/bot.py
my_telegram_bot-1.0.0.dist-info/METADATA
my_telegram_bot-1.0.0.dist-info/WHEEL
my_telegram_bot-1.0.0.dist-info/top_level.txt
my_telegram_bot-1.0.0.dist-info/RECORD
