Metadata-Version: 2.1
Name: my-telegram-bot
Version: 1.0.0
Summary: یک کتابخانه فوق سریع برای ربات تلگرام
Home-page: https://github.com/iliya8989/telegrampx
Author: iliya kaviyani
Author-email: iliyakaviyani313@gmail.com
Classifier: Programming Language :: Python :: 3
Classifier: License :: OSI Approved :: MIT License
Classifier: Operating System :: OS Independent
Requires-Python: >=3.6
Requires-Dist: httpx
Requires-Dist: requests
